COPYING
ChangeLog
MANIFEST.in
README.rst
radio.py
setup.py
test.py
radiopy/__init__.py
radiopy/stations_local.py
radiopy/stations_tunein.py
radiopy.egg-info/PKG-INFO
radiopy.egg-info/SOURCES.txt
radiopy.egg-info/dependency_links.txt
radiopy.egg-info/requires.txt
radiopy.egg-info/top_level.txt
radiopy/data/radiopy.default
radiopy/data/radiopy.default.bak