Metadata-Version: 1.1
Name: radiopy
Version: 0.6
Summary: An interface for mplayer aimed at listening to streaming radio.
Home-page: http://www.guyrutenberg.com/radiopy
Author: Guy Rutenberg
Author-email: guyrutenberg@gmail.com
License: GPLv2+
Platform: UNKNOWN
Classifier: Environment :: Console
Classifier: Intended Audience :: End Users/Desktop
Classifier: License :: OSI Approved :: GNU General Public License v2 or later (GPLv2+)
